custom_settings/__init__.py
custom_settings/tests.py
custom_settings/templatetags/__init__.py
custom_settings/templatetags/custom_settings.py
django_custom_settings_templatetag-1.1.0.dist-info/DESCRIPTION.rst
django_custom_settings_templatetag-1.1.0.dist-info/METADATA
django_custom_settings_templatetag-1.1.0.dist-info/RECORD
django_custom_settings_templatetag-1.1.0.dist-info/WHEEL
django_custom_settings_templatetag-1.1.0.dist-info/metadata.json
django_custom_settings_templatetag-1.1.0.dist-info/top_level.txt
