Metadata-Version: 2.0
Name: django-custom-settings-templatetag
Version: 1.1.0
Summary: Provides a very simple tag to load settings variables from Django templates
Home-page: https://github.com/MickaelBergem/django-custom-settings
Author: Mickaël Bergem
Author-email: suixo@securem.eu
License: MIT
Keywords: django settings configuration template tag
Platform: UNKNOWN
Classifier: Development Status :: 4 - Beta
Classifier: Framework :: Django
Classifier: Environment :: Plugins
Classifier: Intended Audience :: Developers
Classifier: Topic :: Software Development :: Build Tools
Classifier: License :: OSI Approved :: MIT License
Classifier: Programming Language :: Python :: 3
Requires-Dist: django
